labscript-suite.pth
labscript_profile/__init__.py
labscript_profile/create.py
labscript_profile/default_profile/app_saved_configs/README.txt
labscript_profile/default_profile/labconfig/example.ini
labscript_profile/default_profile/userlib/analysislib/__init__.py
labscript_profile/default_profile/userlib/analysislib/common/__init__.py
labscript_profile/default_profile/userlib/analysislib/example_apparatus/example_IMAQdx_remote.py
labscript_profile/default_profile/userlib/labscriptlib/__init__.py
labscript_profile/default_profile/userlib/labscriptlib/common/__init__.py
labscript_profile/default_profile/userlib/labscriptlib/example_apparatus/connection_table.py
labscript_profile/default_profile/userlib/labscriptlib/example_apparatus/connection_table_IMAQdx_remote.py
labscript_profile/default_profile/userlib/labscriptlib/example_apparatus/example_IMAQdx_remote.py
labscript_profile/default_profile/userlib/labscriptlib/example_apparatus/example_experiment.py
labscript_profile/default_profile/userlib/pythonlib/README.txt
labscript_profile/default_profile/userlib/user_devices/README.txt
labscript_utils/__init__.py
labscript_utils/__version__.py
labscript_utils/camera_server.py
labscript_utils/connections.py
labscript_utils/dict_diff.py
labscript_utils/double_import_denier.py
labscript_utils/filewatcher.py
labscript_utils/h5_lock.py
labscript_utils/impprof.py
labscript_utils/labconfig.py
labscript_utils/ls_zprocess.py
labscript_utils/memprof.py
labscript_utils/modulewatcher.py
labscript_utils/properties.py
labscript_utils/remote.py
labscript_utils/settings.py
labscript_utils/setup_logging.py
labscript_utils/shared_drive.py
labscript_utils/shot_utils.py
labscript_utils/splash.py
labscript_utils/testing_utils.py
labscript_utils/tracelog.py
labscript_utils/versions.py
labscript_utils/zlock.py
labscript_utils/zlog.py
labscript_utils/device_registry/__init__.py
labscript_utils/device_registry/_device_registry.py
labscript_utils/excepthook/__init__.py
labscript_utils-3.4.1.dist-info/licenses/LICENSE.txt
labscript_utils-3.4.1.dist-info/METADATA
labscript_utils-3.4.1.dist-info/WHEEL
labscript_utils-3.4.1.dist-info/entry_points.txt
labscript_utils-3.4.1.dist-info/top_level.txt
labscript_utils-3.4.1.dist-info/RECORD
