Metadata-Version: 2.4
Name: labscript-utils
Version: 3.4.1
Summary: Shared utilities for the labscript suite
Author-email: The labscript suite community <labscriptsuite@googlegroups.com>
License: Copyright (c) 2013, Monash University
Project-URL: Homepage, http://labscriptsuite.org/
Project-URL: Documentation, https://docs.labscriptsuite.org/
Project-URL: Repository, https://github.com/labscript-suite/labscript-utils/
Project-URL: Downloads, https://github.com/labscript-suite/labscript-utils/releases/
Project-URL: Tracker, https://github.com/labscript-suite/labscript-utils/issues/
Keywords: experiment control,automation
Classifier: License :: OSI Approved :: BSD License
Classifier: Programming Language :: Python :: 3 :: Only
Requires-Python: >=3.8
License-File: LICENSE.txt
Requires-Dist: h5py>=2.9
Requires-Dist: numpy>=1.15
Requires-Dist: packaging>=20.4
Requires-Dist: pyqtgraph>=0.11.0rc0
Requires-Dist: qtutils>=4.0
Requires-Dist: scipy
Requires-Dist: zprocess>=2.18.0
Requires-Dist: setuptools_scm>=4.1.0
Provides-Extra: docs
Requires-Dist: PyQt5; extra == "docs"
Requires-Dist: Sphinx==8.2.3; extra == "docs"
Requires-Dist: sphinx-rtd-theme==3.0.1; extra == "docs"
Requires-Dist: myst_parser==4.0.1; extra == "docs"
Dynamic: license-file
